tempConverter/__init__.py
tempConverter/tempConverter.py
csc540TempConverterBaynum-1.2.dist-info/METADATA
csc540TempConverterBaynum-1.2.dist-info/WHEEL
csc540TempConverterBaynum-1.2.dist-info/top_level.txt
csc540TempConverterBaynum-1.2.dist-info/RECORD
