Metadata-Version: 2.1
Name: csc540TempConverterBaynum
Version: 1.2
Summary: General purpose temperature converter
Home-page: UNKNOWN
Author: Andy Baynum
Author-email: UNKNOWN
License: UNKNOWN
Platform: UNKNOWN
